lazyml/__init__.py
lazyml-0.0.1.dist-info/LICENSE
lazyml-0.0.1.dist-info/METADATA
lazyml-0.0.1.dist-info/WHEEL
lazyml-0.0.1.dist-info/top_level.txt
lazyml-0.0.1.dist-info/RECORD
