Metadata-Version: 2.1
Name: lazyml
Version: 0.0.1
Summary: Train and Test your data on multiple sklearn models!
Home-page: https://github.com/navendu-pottekkat/lazyml
Author: Navendu Pottekkat
Author-email: navendupottekkat@gmail.com
License: UNKNOWN
Platform: UNKNOWN
Classifier: Programming Language :: Python :: 3
Classifier: License :: OSI Approved :: MIT License
Classifier: Operating System :: OS Independent
Requires-Python: >=3.6
